MANIFEST.in
MIT-LICENSE.txt
README.rst
requirements.txt
setup.py
admin_tools_stats/__init__.py
admin_tools_stats/__init__.pyc
admin_tools_stats/admin.py
admin_tools_stats/admin.pyc
admin_tools_stats/app_label_renamer.py
admin_tools_stats/app_label_renamer.pyc
admin_tools_stats/models.py
admin_tools_stats/models.pyc
admin_tools_stats/modules.py
admin_tools_stats/modules.pyc
admin_tools_stats/tests.py
admin_tools_stats/utils.py
admin_tools_stats/fixtures/10_dashboardstatscriteria_status.json
admin_tools_stats/fixtures/20_dashboardstatscriteria_call_type.json
admin_tools_stats/fixtures/initial_data.json
admin_tools_stats/migrations/0001_initial.py
admin_tools_stats/migrations/0001_initial.pyc
admin_tools_stats/migrations/__init__.py
admin_tools_stats/migrations/__init__.pyc
admin_tools_stats/south_migrations/0001_initial_migration.py
admin_tools_stats/south_migrations/0001_initial_migration.pyc
admin_tools_stats/south_migrations/0002_add_sum_field_name.py
admin_tools_stats/south_migrations/0002_add_sum_field_name.pyc
admin_tools_stats/south_migrations/0003_add_operation_field_name.py
admin_tools_stats/south_migrations/0003_add_operation_field_name.pyc
admin_tools_stats/south_migrations/__init__.py
admin_tools_stats/south_migrations/__init__.pyc
admin_tools_stats/templates/admin_tools_stats/modules/chart.html
demoproject/__init__.py
demoproject/dashboard.py
demoproject/manage.py
demoproject/menu.py
demoproject/demoproject/__init__.py
demoproject/demoproject/settings.py
demoproject/demoproject/urls.py
demoproject/demoproject/views.py
demoproject/demoproject/wsgi.py
django_admin_tools_stats.egg-info/PKG-INFO
django_admin_tools_stats.egg-info/SOURCES.txt
django_admin_tools_stats.egg-info/dependency_links.txt
django_admin_tools_stats.egg-info/not-zip-safe
django_admin_tools_stats.egg-info/requires.txt
django_admin_tools_stats.egg-info/top_level.txt
docs/Makefile
docs/build/doctrees/developer-doc.doctree
docs/build/doctrees/environment.pickle
docs/build/doctrees/index.doctree
docs/build/doctrees/installation-overview.doctree
docs/build/doctrees/introduction.doctree
docs/build/doctrees/developer-doc/modules.doctree
docs/build/doctrees/developer-doc/objects-description.doctree
docs/build/doctrees/developer-doc/pre-requisite.doctree
