Metadata-Version: 1.1
Name: django-admin-tools-stats
Version: 0.6.5
Summary: django-admin-tools-stats - Django-admin module to create charts and stats in your dashboard
Home-page: http://github.com/Star2Billing/django-admin-tools-stats
Author: Belaid Arezqui
Author-email: areski@gmail.com
License: MIT License
Platform: UNKNOWN
Classifier: Development Status :: 5 - Production/Stable
Classifier: Environment :: Web Environment
Classifier: Framework :: Django
Classifier: Intended Audience :: Developers
Classifier: License :: OSI Approved :: MIT License
Classifier: Operating System :: OS Independent
Classifier: Programming Language :: Python
Classifier: Programming Language :: Python :: 2
Classifier: Programming Language :: Python :: 2.6
Classifier: Programming Language :: Python :: 2.7
Classifier: Topic :: Software Development :: Libraries :: Python Modules
